eld/__init__.py
eld/languageData.py
eld/languageDetector.py
eld/languageResult.py
eld/languageSubset.py
eld/resources/avg_score.py
eld/resources/ngrams/ngramsL60.py
eld/resources/ngrams/ngramsM60.py
eld/resources/ngrams/subset/ngramsM60-1_2rrx014rx6ypsas6tplo1gtcnmiv5mz.py
eld/resources/ngrams/subset/ngramsM60-6_5ijqhj4oecs310zqtm8u9pgmd9ox2yd.py
eld/subsetResult.py
eld/tests/data/big-test.txt
eld/tests/test_detector.py
eld/tests/test_subset.py
eld-1.0.6.dist-info/LICENSE
eld-1.0.6.dist-info/METADATA
eld-1.0.6.dist-info/WHEEL
eld-1.0.6.dist-info/RECORD
