Metadata-Version: 2.1
Name: eld
Version: 1.0.6
Summary: Fast and accurate natural language detection. Detector written in Python. Nito-ELD, ELD.
Home-page: https://github.com/nitotm/efficient-language-detector-py/
License: Apache-2.0
Keywords: nlp,language,natural-language-processing,natural-language,language-detection,language-detector,language-identification
Author: Nito T.M.
Requires-Python: >=3.7,<4.0
Classifier: License :: OSI Approved :: Apache Software License
Classifier: Operating System :: OS Independent
Classifier: Programming Language :: Python :: 3
Classifier: Programming Language :: Python :: 3.7
Classifier: Programming Language :: Python :: 3.8
Classifier: Programming Language :: Python :: 3.9
Classifier: Programming Language :: Python :: 3.10
Classifier: Programming Language :: Python :: 3.11
Classifier: Programming Language :: Python :: 3
Requires-Dist: regex
Project-URL: Repository, https://github.com/nitotm/efficient-language-detector-py.git
